schedule_decorator/__init__.py
schedule_decorator/schedule_decorator.py
schedule_decorator-2.1.2.dist-info/LICENSE
schedule_decorator-2.1.2.dist-info/METADATA
schedule_decorator-2.1.2.dist-info/WHEEL
schedule_decorator-2.1.2.dist-info/top_level.txt
schedule_decorator-2.1.2.dist-info/RECORD
