Metadata-Version: 2.1
Name: schedule-decorator
Version: 2.1.2
Summary: A wonderful decorator package from schedule!
Home-page: https://github.com/miloira/schedule-decorator
Author: Msky
Author-email: 690126048@qq.com
License: UNKNOWN
Platform: UNKNOWN
License-File: LICENSE
Requires-Dist: schedule
